MANIFEST.in
README.md
setup.cfg
setup.py
cli/__init__.py
cli/webpype-cli.py
examples/basic_get_options.py
webpype/__init__.py
webpype/client.py
webpype/server.py
webpype.egg-info/PKG-INFO
webpype.egg-info/SOURCES.txt
webpype.egg-info/dependency_links.txt
webpype.egg-info/entry_points.txt
webpype.egg-info/top_level.txt
webpype.egg-info/zip-safe