Metadata-Version: 1.0
Name: webpype
Version: 0.1.2dev
Summary: Python library for WebPipes
Home-page: https://github.com/ajvb/webpype
Author: AJ Bahnken
Author-email: aj@ajvb.me
License: Apache License v2
Keywords: web json webpipe
Platform: UNKNOWN
